[
    {
        "garageName": "Garage A",
        "total": "1647",
        "available": "1537",
        "occupiedPercent": "7",
        "occupiedProgressText": "▰",
        "nonOccupiedProgressText": "▱▱▱▱▱▱▱▱▱"
    },
    {
        "garageName": "Garage B",
        "total": "1289",
        "available": "944",
        "occupiedPercent": "27",
        "occupiedProgressText": "▰▰",
        "nonOccupiedProgressText": "▱▱▱▱▱▱▱▱"
    },
    {
        "garageName": "Garage C",
        "total": "1852",
        "available": "596",
        "occupiedPercent": "68",
        "occupiedProgressText": "▰▰▰▰▰▰",
        "nonOccupiedProgressText": "▱▱▱▱"
    },
    {
        "garageName": "Garage D",
        "total": "1289",
        "available": "732",
        "occupiedPercent": "43",
        "occupiedProgressText": "▰▰▰▰",
        "nonOccupiedProgressText": "▱▱▱▱▱▱"
    },
    {
        "garageName": "Garage H",
        "total": "1340",
        "available": "509",
        "occupiedPercent": "62",
        "occupiedProgressText": "▰▰▰▰▰▰",
        "nonOccupiedProgressText": "▱▱▱▱"
    },
    {
        "garageName": "Garage I",
        "total": "1270",
        "available": "1253",
        "occupiedPercent": "1",
        "occupiedProgressText": "▰",
        "nonOccupiedProgressText": "▱▱▱▱▱▱▱▱▱"
    },
    {
        "garageName": "Downtown Campus Amelia Garage",
        "total": "603",
        "available": "558",
        "occupiedPercent": "7",
        "occupiedProgressText": "▰",
        "nonOccupiedProgressText": "▱▱▱▱▱▱▱▱▱"
    },
    {
        "garageName": "Downtown Campus Parramore Garage",
        "total": "571",
        "available": "376",
        "occupiedPercent": "34",
        "occupiedProgressText": "▰▰▰",
        "nonOccupiedProgressText": "▱▱▱▱▱▱▱"
    },
    {
        "garageName": "Rosen Lot",
        "total": "571",
        "available": "541",
        "occupiedPercent": "5",
        "occupiedProgressText": "▰",
        "nonOccupiedProgressText": "▱▱▱▱▱▱▱▱▱"
    }
]