[
    {
        "garageName": "Garage A",
        "total": "1647",
        "available": "1488",
        "occupiedPercent": "10",
        "occupiedProgressText": "▰",
        "nonOccupiedProgressText": "▱▱▱▱▱▱▱▱▱"
    },
    {
        "garageName": "Garage B",
        "total": "1229",
        "available": "1229",
        "occupiedPercent": "0",
        "occupiedProgressText": "▱",
        "nonOccupiedProgressText": "▱▱▱▱▱▱▱▱▱"
    },
    {
        "garageName": "Garage C",
        "total": "1852",
        "available": "1852",
        "occupiedPercent": "0",
        "occupiedProgressText": "▱",
        "nonOccupiedProgressText": "▱▱▱▱▱▱▱▱▱"
    },
    {
        "garageName": "Garage D",
        "total": "1289",
        "available": "575",
        "occupiedPercent": "55",
        "occupiedProgressText": "▰▰▰▰▰",
        "nonOccupiedProgressText": "▱▱▱▱▱"
    },
    {
        "garageName": "Garage H",
        "total": "1310",
        "available": "963",
        "occupiedPercent": "26",
        "occupiedProgressText": "▰▰",
        "nonOccupiedProgressText": "▱▱▱▱▱▱▱▱"
    },
    {
        "garageName": "Garage I",
        "total": "1270",
        "available": "1270",
        "occupiedPercent": "0",
        "occupiedProgressText": "▱",
        "nonOccupiedProgressText": "▱▱▱▱▱▱▱▱▱"
    },
    {
        "garageName": "Downtown Campus Amelia Garage",
        "total": "603",
        "available": "603",
        "occupiedPercent": "0",
        "occupiedProgressText": "▱",
        "nonOccupiedProgressText": "▱▱▱▱▱▱▱▱▱"
    },
    {
        "garageName": "Downtown Campus Parramore Garage",
        "total": "571",
        "available": "495",
        "occupiedPercent": "13",
        "occupiedProgressText": "▰",
        "nonOccupiedProgressText": "▱▱▱▱▱▱▱▱▱"
    },
    {
        "garageName": "Rosen Lot",
        "total": "571",
        "available": "478",
        "occupiedPercent": "16",
        "occupiedProgressText": "▰",
        "nonOccupiedProgressText": "▱▱▱▱▱▱▱▱▱"
    }
]