[
    {
        "garageName": "Garage A",
        "total": "1647",
        "available": "1534",
        "occupiedPercent": "7",
        "occupiedProgressText": "▰",
        "nonOccupiedProgressText": "▱▱▱▱▱▱▱▱▱"
    },
    {
        "garageName": "Garage B",
        "total": "1289",
        "available": "892",
        "occupiedPercent": "31",
        "occupiedProgressText": "▰▰▰",
        "nonOccupiedProgressText": "▱▱▱▱▱▱▱"
    },
    {
        "garageName": "Garage C",
        "total": "1792",
        "available": "1413",
        "occupiedPercent": "21",
        "occupiedProgressText": "▰▰",
        "nonOccupiedProgressText": "▱▱▱▱▱▱▱▱"
    },
    {
        "garageName": "Garage D",
        "total": "1289",
        "available": "445",
        "occupiedPercent": "65",
        "occupiedProgressText": "▰▰▰▰▰▰",
        "nonOccupiedProgressText": "▱▱▱▱"
    },
    {
        "garageName": "Garage H",
        "total": "1340",
        "available": "0",
        "occupiedPercent": "100",
        "occupiedProgressText": "▰▰▰▰▰▰▰▰▰▰",
        "nonOccupiedProgressText": ""
    },
    {
        "garageName": "Garage I",
        "total": "1270",
        "available": "0",
        "occupiedPercent": "100",
        "occupiedProgressText": "▰▰▰▰▰▰▰▰▰▰",
        "nonOccupiedProgressText": ""
    },
    {
        "garageName": "Downtown Campus Amelia Garage",
        "total": "603",
        "available": "575",
        "occupiedPercent": "5",
        "occupiedProgressText": "▰",
        "nonOccupiedProgressText": "▱▱▱▱▱▱▱▱▱"
    },
    {
        "garageName": "Downtown Campus Parramore Garage",
        "total": "571",
        "available": "333",
        "occupiedPercent": "42",
        "occupiedProgressText": "▰▰▰▰",
        "nonOccupiedProgressText": "▱▱▱▱▱▱"
    },
    {
        "garageName": "Rosen Lot",
        "total": "571",
        "available": "426",
        "occupiedPercent": "25",
        "occupiedProgressText": "▰▰",
        "nonOccupiedProgressText": "▱▱▱▱▱▱▱▱"
    }
]